eldar_mafia/__init__.py
eldar_mafia/game.py
eldar_mafia-1.0.0.dist-info/METADATA
eldar_mafia-1.0.0.dist-info/WHEEL
eldar_mafia-1.0.0.dist-info/entry_points.txt
eldar_mafia-1.0.0.dist-info/top_level.txt
eldar_mafia-1.0.0.dist-info/RECORD
