Metadata-Version: 2.4
Name: eldar-mafia
Version: 1.0.0
Summary: CLI Mafia Game (Group Moderator Game)
Author: Eldar
Requires-Python: >=3.8
